visast/__init__.py
visast/generate.py
visast/visualise.py
VisAST-1.0.1.dist-info/LICENSE
VisAST-1.0.1.dist-info/METADATA
VisAST-1.0.1.dist-info/WHEEL
VisAST-1.0.1.dist-info/top_level.txt
VisAST-1.0.1.dist-info/RECORD
