Metadata-Version: 2.1
Name: VisAST
Version: 1.0.1
Summary: Building and visualising Abstract Syntax Trees for Python code.
Home-page: https://github.com/JamesPhillipsUK/vast
Author: Jesse Phillips
Author-email: james@jamesphillipsuk.com
Project-URL: Bug Tracker, https://github.com/JamesPhillipsUK/vast/issues
Classifier: Programming Language :: Python :: 3
Classifier: License :: OSI Approved :: GNU General Public License v3 or later (GPLv3+)
Classifier: Operating System :: OS Independent
Requires-Python: >=3.9
License-File: LICENSE
Requires-Dist: networkx
Requires-Dist: EoN
Requires-Dist: matplotlib
